developeralex_hello_team-0.1.0.dist-info/licenses/LICENSE
hello_team/__init__.py
hello_team/hello_team.py
developeralex_hello_team-0.1.0.dist-info/METADATA
developeralex_hello_team-0.1.0.dist-info/WHEEL
developeralex_hello_team-0.1.0.dist-info/top_level.txt
developeralex_hello_team-0.1.0.dist-info/RECORD
