Metadata-Version: 2.4
Name: developeralex-hello-team
Version: 0.1.0
Summary: A colorful Python package that greets teams with style using colorama
Home-page: https://github.com/DeveloperAlex/pypi_HelloTeam
Author: DeveloperAlex
License: MIT
Project-URL: Homepage, https://github.com/DeveloperAlex/pypi_HelloTeam
Project-URL: Repository, https://github.com/DeveloperAlex/pypi_HelloTeam
Project-URL: Bug Tracker, https://github.com/DeveloperAlex/pypi_HelloTeam/issues
Keywords: colorama,greeting,team,terminal,colors,cli,console
Classifier: Development Status :: 4 - Beta
Classifier: Intended Audience :: Developers
Classifier: License :: OSI Approved :: MIT License
Classifier: Operating System :: OS Independent
Classifier: Programming Language :: Python :: 3
Classifier: Programming Language :: Python :: 3.10
Classifier: Programming Language :: Python :: 3.11
Classifier: Programming Language :: Python :: 3.12
Classifier: Programming Language :: Python :: 3.13
Classifier: Programming Language :: Python :: 3.14
Classifier: Topic :: Software Development :: Libraries :: Python Modules
Classifier: Topic :: Terminals
Classifier: Topic :: Utilities
Requires-Python: >=3.6
License-File: LICENSE
Requires-Dist: colorama>=0.4.0
Dynamic: home-page
Dynamic: license-file
Dynamic: requires-python
